{
  "spots": [
    {
      "no": 0,
      "x": 601,
      "y": 351
    },
    {
      "no": 1,
      "x": 605,
      "y": 429
    },
    {
      "no": 2,
      "x": 669,
      "y": 485
    },
    {
      "no": 3,
      "x": 789,
      "y": 502
    },
    {
      "no": 4,
      "x": 512,
      "y": 467
    },
    {
      "no": 5,
      "x": 371,
      "y": 421
    },
    {
      "no": 6,
      "x": 271,
      "y": 351
    },
    {
      "no": 7,
      "x": 196,
      "y": 429
    },
    {
      "no": 8,
      "x": 140,
      "y": 316
    },
    {
      "no": 24,
      "x": 880,
      "y": 451
    },
    {
      "no": 25,
      "x": 999,
      "y": 431
    },
    {
      "no": 26,
      "x": 915,
      "y": 328
    },
    {
      "no": 27,
      "x": 867,
      "y": 268
    },
    {
      "no": 28,
      "x": 998,
      "y": 290
    },
    {
      "no": 29,
      "x": 966,
      "y": 181
    },
    {
      "no": 30,
      "x": 915,
      "y": 328
    },
    {
      "no": 31,
      "x": 998,
      "y": 290
    },
    {
      "no": 32,
      "x": 770,
      "y": 271
    },
    {
      "no": 33,
      "x": 779,
      "y": 348
    },
    {
      "no": 34,
      "x": 1031,
      "y": 178
    },
    {
      "no": 35,
      "x": 779,
      "y": 348
    },
    {
      "no": 36,
      "x": 880,
      "y": 451
    },
    {
      "no": 37,
      "x": 915,
      "y": 328
    },
    {
      "no": 38,
      "x": 763,
      "y": 191
    },
    {
      "no": 9,
      "x": 473,
      "y": 404
    },
    {
      "no": 10,
      "x": 554,
      "y": 534
    },
    {
      "no": 11,
      "x": 440,
      "y": 496
    },
    {
      "no": 12,
      "x": 352,
      "y": 531
    },
    {
      "no": 13,
      "x": 287,
      "y": 446
    },
    {
      "no": 14,
      "x": 400,
      "y": 379
    },
    {
      "no": 15,
      "x": 380,
      "y": 306
    },
    {
      "no": 16,
      "x": 461,
      "y": 297
    },
    {
      "no": 17,
      "x": 417,
      "y": 271
    },
    {
      "no": 18,
      "x": 440,
      "y": 224
    },
    {
      "no": 19,
      "x": 375,
      "y": 190
    },
    {
      "no": 20,
      "x": 417,
      "y": 271
    },
    {
      "no": 21,
      "x": 512,
      "y": 467
    },
    {
      "no": 22,
      "x": 440,
      "y": 496
    },
    {
      "no": 23,
      "x": 522,
      "y": 331
    }
  ]
}